xompass_sync/__init__.py
xompass_sync/sync.py
xompass_sync-0.4.0.dist-info/METADATA
xompass_sync-0.4.0.dist-info/WHEEL
xompass_sync-0.4.0.dist-info/top_level.txt
xompass_sync-0.4.0.dist-info/RECORD
